gudio/__init__.py
gudio/decoder/vae.safetensors
gudio/encoder/codec.pt
gudio/encoder/tokenizer.json
gudio/perth/__init__.py
gudio/perth/config.py
gudio/perth/dummy_watermarker.py
gudio/perth/utils.py
gudio/perth/watermarker.py
gudio/perth/waveform.py
gudio/perth/cli/__init__.py
gudio/perth/cli/watermark_cli.py
gudio/perth/perth_net/__init__.py
gudio/perth/perth_net/perth_net_implicit/__init__.py
gudio/perth/perth_net/perth_net_implicit/audio_processor.py
gudio/perth/perth_net/perth_net_implicit/checkpoint_manager.py
gudio/perth/perth_net/perth_net_implicit/config.py
gudio/perth/perth_net/perth_net_implicit/perth_watermarker.py
gudio/perth/perth_net/perth_net_implicit/utils.py
gudio/perth/perth_net/perth_net_implicit/model/__init__.py
gudio/perth/perth_net/perth_net_implicit/model/decoder.py
gudio/perth/perth_net/perth_net_implicit/model/encoder.py
gudio/perth/perth_net/perth_net_implicit/model/perth_net.py
gudio/perth/perth_net/pretrained/implicit/hparams.yaml
gudio/perth/perth_net/pretrained/implicit/id.txt
gudio/perth/perth_net/pretrained/implicit/perth_net_250000.pth.tar
gudio/tool/__init__.py
gudio/tool/models/s3gen/__init__.py
gudio/tool/models/s3gen/const.py
gudio/tool/models/s3gen/decoder.py
gudio/tool/models/s3gen/f0_predictor.py
gudio/tool/models/s3gen/flow.py
gudio/tool/models/s3gen/flow_matching.py
gudio/tool/models/s3gen/hifigan.py
gudio/tool/models/s3gen/s3gen.py
gudio/tool/models/s3gen/xvector.py
gudio/tool/models/s3gen/matcha/decoder.py
gudio/tool/models/s3gen/matcha/flow_matching.py
gudio/tool/models/s3gen/matcha/text_encoder.py
gudio/tool/models/s3gen/matcha/transformer.py
gudio/tool/models/s3gen/transformer/__init__.py
gudio/tool/models/s3gen/transformer/activation.py
gudio/tool/models/s3gen/transformer/attention.py
gudio/tool/models/s3gen/transformer/convolution.py
gudio/tool/models/s3gen/transformer/embedding.py
gudio/tool/models/s3gen/transformer/encoder_layer.py
gudio/tool/models/s3gen/transformer/positionwise_feed_forward.py
gudio-0.0.3.dist-info/LICENSE
gudio-0.0.3.dist-info/WHEEL
gudio-0.0.3.dist-info/METADATA
gudio-0.0.3.dist-info/RECORD
