Metadata-Version: 2.1
Name: gudio
Version: 0.0.3
Summary: gudio toolkit
Author-email: calcuis <info@calcu.io>
Classifier: License :: OSI Approved :: MIT License
Requires-Dist: librosa
Requires-Dist: s3tokenizer
Requires-Dist: omegaconf
Project-URL: GitHub, https://github.com/calcuis/gudio
